{
    "bUserExists": true,
    "bProfileIsPrivate": false,
    "bTooManyRequestsError": false,
    "sScrapedUrl": "https://profiles.udacity.com/u/felix",
    "sScrapedUserId": "felix",
    "sProfileLastUpdate": "Profile last updated 9 months ago",
    "sName": "Felix Prados",
    "sLocation": "Santa Perpètua de Mogoda, Spain",
    "sEmail": "",
    "sStateOrCountry": "Spain",
    "sImageUrl": "https://s3-us-west-2.amazonaws.com/udacity-profiles/production/photo/4583014206.jpg#1523500318429",
    "iDetailCount": 0,
    "iCountOfNanodegrees": 0,
    "iEducationCount": 0,
    "iExperienceCount": 0,
    "bPresentlyEmployed": false,
    "iAgeEstimate": null,
    "sLanguagesSpoken": "Spanish, Catalan, English, French",
    "sImageOnGithubUrl": "https://raw.githubusercontent.com/Vandivier/data-science-practice/master/js/udacity-study/manually-scraped/profile-pics/felix.jpg",
    "sInputLocation": "manually-scraped/4-11-sample/felix.txt",
    "sInputBaseName": "4-11-sample",
    "sOutputDirectory": "manually-scraped/4-11-sample - processed",
    "sOutputLocation": "manually-scraped/4-11-sample - processed/felix.json",
    "bNameTruncated": false,
    "sNameAsReported": "Felix Prados",
    "sNameWithoutSuffix": "Felix Prados",
    "sNameWithoutInitials": "Felix Prados",
    "sNameFirst": "Felix",
    "sNameFirstLowercased": "felix",
    "oCachedData": {
        "bUserExists": true,
        "bProfileIsPrivate": false,
        "bTooManyRequestsError": false,
        "sScrapedUrl": "https://profiles.udacity.com/u/felix",
        "sScrapedUserId": "felix",
        "sProfileLastUpdate": "Profile last updated 9 months ago",
        "sName": "Felix Prados",
        "sLocation": "Santa Perpètua de Mogoda, Spain",
        "sEmail": "",
        "sStateOrCountry": "Spain",
        "sImageUrl": "https://s3-us-west-2.amazonaws.com/udacity-profiles/production/photo/4583014206.jpg#1523500318429",
        "iDetailCount": 0,
        "iCountOfNanodegrees": 0,
        "iEducationCount": 0,
        "iExperienceCount": 0,
        "bPresentlyEmployed": false,
        "iAgeEstimate": null,
        "sLanguagesSpoken": "Spanish, Catalan, English, French",
        "sImageOnGithubUrl": "https://raw.githubusercontent.com/Vandivier/data-science-practice/master/js/udacity-study/manually-scraped/profile-pics/felix.jpg",
        "sInputLocation": "manually-scraped/4-11-sample/felix.txt",
        "sInputBaseName": "4-11-sample",
        "sOutputDirectory": "manually-scraped/4-11-sample - processed",
        "sOutputLocation": "manually-scraped/4-11-sample - processed/felix.json",
        "bNameTruncated": false,
        "sNameAsReported": "Felix Prados",
        "sNameWithoutSuffix": "Felix Prados",
        "sNameWithoutInitials": "Felix Prados",
        "sNameFirst": "Felix",
        "sNameFirstLowercased": "felix",
        "bKairosImageSubmitted": true,
        "iKairosAge": 47,
        "iKairosAsian": 0.00027,
        "iKairosBlack": 0.00026,
        "iKairosMaleConfidence": 0.99993,
        "iKairosHispanic": 0.02339,
        "iKairosOtherEthnicity": 0.00212,
        "iKairosWhite": 0.97397,
        "iLanguagesSpoken": 4,
        "bSpeaksEnglish": true,
        "bSpeaksSpanish": true,
        "bSpeaksOther": true,
        "sCountry": "Spain",
        "bGithubAccountClaimed": false,
        "bGitHubAccountFound": false,
        "bLinkedInAccountClaimed": false,
        "bLinkedInAccountFound": false,
        "iNamePrismTwoPrace": 0.0018743432189290822,
        "iNamePrismHispanic": 0.3402163024647278,
        "iNamePrismApi": 0.002024773448721632,
        "iNamePrismBlack": 0.04134006688542448,
        "iNamePrismAsian": 0.00024512898086727233,
        "iNamePrismWhite": 0.6142993850013297,
        "iNamePrism-Jewish": 0.0000020509025663778063,
        "iNamePrism-Nordic-Finland": 7.694219081922193e-7,
        "iNamePrism-Greek": 0.0000030797149276811614,
        "iNamePrism-SouthAsian": 0.00008026660140548248,
        "iNamePrism-CelticEnglish": 0.0028792637404155947,
        "iNamePrism-Hispanic-Philippines": 0.0001152498004142045,
        "iNamePrism-Hispanic-Spanish": 0.9616225867304649,
        "iNamePrism-Hispanic-Portuguese": 0.009446459038713441,
        "iNamePrism-African-EastAfrican": 0.00022456176394443147,
        "iNamePrism-African-WestAfrican": 0.0001689356995488703,
        "iNamePrism-African-SouthAfrican": 0.000008972882339957833,
        "iNamePrism-EastAsian-Japan": 7.698038331935378e-7,
        "iNamePrism-EastAsian-Chinese": 0.0001425591644757887,
        "iNamePrism-EastAsian-South Korea": 5.134937092267437e-7,
        "iNamePrism-Muslim-Persian": 0.000013335124423711518,
        "iNamePrism-Muslim-Maghreb": 5.898090244919659e-10,
        "iNamePrism-Muslim-Nubian": 0.000001288664666440308,
        "iNamePrism-Muslim-ArabianPeninsula": 5.147868148621526e-7,
        "iNamePrism-European-SouthSlavs": 6.888054999540994e-7,
        "iNamePrism-European-Baltics": 4.5887837430488916e-7,
        "iNamePrism-European-French": 0.008008564463812727,
        "iNamePrism-European-Russian": 0.0000066528109505664696,
        "iNamePrism-European-EastEuropean": 0.0000018355974342669408,
        "iNamePrism-European-German": 0.016930560335513458
    },
    "bKairosImageSubmitted": true,
    "iKairosAge": 47,
    "iKairosAsian": 0.00027,
    "iKairosBlack": 0.00026,
    "iKairosMaleConfidence": 0.99993,
    "iKairosHispanic": 0.02339,
    "iKairosOtherEthnicity": 0.00212,
    "iKairosWhite": 0.97397,
    "iLanguagesSpoken": 4,
    "bSpeaksEnglish": true,
    "bSpeaksSpanish": true,
    "bSpeaksOther": true,
    "sCountry": "Spain",
    "bGithubAccountClaimed": false,
    "bGitHubAccountFound": false,
    "bLinkedInAccountClaimed": false,
    "bLinkedInAccountFound": false,
    "iNamePrismTwoPrace": 0.0018743432189290822,
    "iNamePrismHispanic": 0.3402163024647278,
    "iNamePrismApi": 0.002024773448721632,
    "iNamePrismBlack": 0.04134006688542448,
    "iNamePrismAsian": 0.00024512898086727233,
    "iNamePrismWhite": 0.6142993850013297,
    "iNamePrismsNameAsReported-Jewish": 0.0000020509025663778063,
    "iNamePrismsNameAsReported-Nordic-Finland": 7.694219081922193e-7,
    "iNamePrismsNameAsReported-Greek": 0.0000030797149276811614,
    "iNamePrismsNameAsReported-SouthAsian": 0.00008026660140548248,
    "iNamePrismsNameAsReported-CelticEnglish": 0.0028792637404155947,
    "iNamePrismsNameAsReported-Hispanic-Philippines": 0.0001152498004142045,
    "iNamePrismsNameAsReported-Hispanic-Spanish": 0.9616225867304649,
    "iNamePrismsNameAsReported-Hispanic-Portuguese": 0.009446459038713441,
    "iNamePrismsNameAsReported-African-EastAfrican": 0.00022456176394443147,
    "iNamePrismsNameAsReported-African-WestAfrican": 0.0001689356995488703,
    "iNamePrismsNameAsReported-African-SouthAfrican": 0.000008972882339957833,
    "iNamePrismsNameAsReported-EastAsian-Japan": 7.698038331935378e-7,
    "iNamePrismsNameAsReported-EastAsian-Chinese": 0.0001425591644757887,
    "iNamePrismsNameAsReported-EastAsian-South Korea": 5.134937092267437e-7,
    "iNamePrismsNameAsReported-Muslim-Persian": 0.000013335124423711518,
    "iNamePrismsNameAsReported-Muslim-Maghreb": 5.898090244919659e-10,
    "iNamePrismsNameAsReported-Muslim-Nubian": 0.000001288664666440308,
    "iNamePrismsNameAsReported-Muslim-ArabianPeninsula": 5.147868148621526e-7,
    "iNamePrismsNameAsReported-European-SouthSlavs": 6.888054999540994e-7,
    "iNamePrismsNameAsReported-European-Baltics": 4.5887837430488916e-7,
    "iNamePrismsNameAsReported-European-French": 0.008008564463812727,
    "iNamePrismsNameAsReported-European-Russian": 0.0000066528109505664696,
    "iNamePrismsNameAsReported-European-EastEuropean": 0.0000018355974342669408,
    "iNamePrismsNameAsReported-European-German": 0.016930560335513458,
    "iNamePrismsNameWithoutSuffix-Jewish": 0.0000020509025663778063,
    "iNamePrismsNameWithoutSuffix-Nordic-Finland": 7.694219081922193e-7,
    "iNamePrismsNameWithoutSuffix-Greek": 0.0000030797149276811614,
    "iNamePrismsNameWithoutSuffix-SouthAsian": 0.00008026660140548248,
    "iNamePrismsNameWithoutSuffix-CelticEnglish": 0.0028792637404155947,
    "iNamePrismsNameWithoutSuffix-Hispanic-Philippines": 0.0001152498004142045,
    "iNamePrismsNameWithoutSuffix-Hispanic-Spanish": 0.9616225867304649,
    "iNamePrismsNameWithoutSuffix-Hispanic-Portuguese": 0.009446459038713441,
    "iNamePrismsNameWithoutSuffix-African-EastAfrican": 0.00022456176394443147,
    "iNamePrismsNameWithoutSuffix-African-WestAfrican": 0.0001689356995488703,
    "iNamePrismsNameWithoutSuffix-African-SouthAfrican": 0.000008972882339957833,
    "iNamePrismsNameWithoutSuffix-EastAsian-Japan": 7.698038331935378e-7,
    "iNamePrismsNameWithoutSuffix-EastAsian-Chinese": 0.0001425591644757887,
    "iNamePrismsNameWithoutSuffix-EastAsian-South Korea": 5.134937092267437e-7,
    "iNamePrismsNameWithoutSuffix-Muslim-Persian": 0.000013335124423711518,
    "iNamePrismsNameWithoutSuffix-Muslim-Maghreb": 5.898090244919659e-10,
    "iNamePrismsNameWithoutSuffix-Muslim-Nubian": 0.000001288664666440308,
    "iNamePrismsNameWithoutSuffix-Muslim-ArabianPeninsula": 5.147868148621526e-7,
    "iNamePrismsNameWithoutSuffix-European-SouthSlavs": 6.888054999540994e-7,
    "iNamePrismsNameWithoutSuffix-European-Baltics": 4.5887837430488916e-7,
    "iNamePrismsNameWithoutSuffix-European-French": 0.008008564463812727,
    "iNamePrismsNameWithoutSuffix-European-Russian": 0.0000066528109505664696,
    "iNamePrismsNameWithoutSuffix-European-EastEuropean": 0.0000018355974342669408,
    "iNamePrismsNameWithoutSuffix-European-German": 0.016930560335513458,
    "iNamePrismsNameWithoutInitials-Jewish": 0.0000020509025663778063,
    "iNamePrismsNameWithoutInitials-Nordic-Finland": 7.694219081922193e-7,
    "iNamePrismsNameWithoutInitials-Greek": 0.0000030797149276811614,
    "iNamePrismsNameWithoutInitials-SouthAsian": 0.00008026660140548248,
    "iNamePrismsNameWithoutInitials-CelticEnglish": 0.0028792637404155947,
    "iNamePrismsNameWithoutInitials-Hispanic-Philippines": 0.0001152498004142045,
    "iNamePrismsNameWithoutInitials-Hispanic-Spanish": 0.9616225867304649,
    "iNamePrismsNameWithoutInitials-Hispanic-Portuguese": 0.009446459038713441,
    "iNamePrismsNameWithoutInitials-African-EastAfrican": 0.00022456176394443147,
    "iNamePrismsNameWithoutInitials-African-WestAfrican": 0.0001689356995488703,
    "iNamePrismsNameWithoutInitials-African-SouthAfrican": 0.000008972882339957833,
    "iNamePrismsNameWithoutInitials-EastAsian-Japan": 7.698038331935378e-7,
    "iNamePrismsNameWithoutInitials-EastAsian-Chinese": 0.0001425591644757887,
    "iNamePrismsNameWithoutInitials-EastAsian-South Korea": 5.134937092267437e-7,
    "iNamePrismsNameWithoutInitials-Muslim-Persian": 0.000013335124423711518,
    "iNamePrismsNameWithoutInitials-Muslim-Maghreb": 5.898090244919659e-10,
    "iNamePrismsNameWithoutInitials-Muslim-Nubian": 0.000001288664666440308,
    "iNamePrismsNameWithoutInitials-Muslim-ArabianPeninsula": 5.147868148621526e-7,
    "iNamePrismsNameWithoutInitials-European-SouthSlavs": 6.888054999540994e-7,
    "iNamePrismsNameWithoutInitials-European-Baltics": 4.5887837430488916e-7,
    "iNamePrismsNameWithoutInitials-European-French": 0.008008564463812727,
    "iNamePrismsNameWithoutInitials-European-Russian": 0.0000066528109505664696,
    "iNamePrismsNameWithoutInitials-European-EastEuropean": 0.0000018355974342669408,
    "iNamePrismsNameWithoutInitials-European-German": 0.016930560335513458,
    "iNamePrismsNameFirst-Jewish": 0.0000020509025663778063,
    "iNamePrismsNameFirst-Nordic-Finland": 7.694219081922193e-7,
    "iNamePrismsNameFirst-Greek": 0.0000030797149276811614,
    "iNamePrismsNameFirst-SouthAsian": 0.00008026660140548248,
    "iNamePrismsNameFirst-CelticEnglish": 0.0028792637404155947,
    "iNamePrismsNameFirst-Hispanic-Philippines": 0.0001152498004142045,
    "iNamePrismsNameFirst-Hispanic-Spanish": 0.9616225867304649,
    "iNamePrismsNameFirst-Hispanic-Portuguese": 0.009446459038713441,
    "iNamePrismsNameFirst-African-EastAfrican": 0.00022456176394443147,
    "iNamePrismsNameFirst-African-WestAfrican": 0.0001689356995488703,
    "iNamePrismsNameFirst-African-SouthAfrican": 0.000008972882339957833,
    "iNamePrismsNameFirst-EastAsian-Japan": 7.698038331935378e-7,
    "iNamePrismsNameFirst-EastAsian-Chinese": 0.0001425591644757887,
    "iNamePrismsNameFirst-EastAsian-South Korea": 5.134937092267437e-7,
    "iNamePrismsNameFirst-Muslim-Persian": 0.000013335124423711518,
    "iNamePrismsNameFirst-Muslim-Maghreb": 5.898090244919659e-10,
    "iNamePrismsNameFirst-Muslim-Nubian": 0.000001288664666440308,
    "iNamePrismsNameFirst-Muslim-ArabianPeninsula": 5.147868148621526e-7,
    "iNamePrismsNameFirst-European-SouthSlavs": 6.888054999540994e-7,
    "iNamePrismsNameFirst-European-Baltics": 4.5887837430488916e-7,
    "iNamePrismsNameFirst-European-French": 0.008008564463812727,
    "iNamePrismsNameFirst-European-Russian": 0.0000066528109505664696,
    "iNamePrismsNameFirst-European-EastEuropean": 0.0000018355974342669408,
    "iNamePrismsNameFirst-European-German": 0.016930560335513458,
    "iNamePrismsNameFirstLowercased-Jewish": 0.0000020509025663778063,
    "iNamePrismsNameFirstLowercased-Nordic-Finland": 7.694219081922193e-7,
    "iNamePrismsNameFirstLowercased-Greek": 0.0000030797149276811614,
    "iNamePrismsNameFirstLowercased-SouthAsian": 0.00008026660140548248,
    "iNamePrismsNameFirstLowercased-CelticEnglish": 0.0028792637404155947,
    "iNamePrismsNameFirstLowercased-Hispanic-Philippines": 0.0001152498004142045,
    "iNamePrismsNameFirstLowercased-Hispanic-Spanish": 0.9616225867304649,
    "iNamePrismsNameFirstLowercased-Hispanic-Portuguese": 0.009446459038713441,
    "iNamePrismsNameFirstLowercased-African-EastAfrican": 0.00022456176394443147,
    "iNamePrismsNameFirstLowercased-African-WestAfrican": 0.0001689356995488703,
    "iNamePrismsNameFirstLowercased-African-SouthAfrican": 0.000008972882339957833,
    "iNamePrismsNameFirstLowercased-EastAsian-Japan": 7.698038331935378e-7,
    "iNamePrismsNameFirstLowercased-EastAsian-Chinese": 0.0001425591644757887,
    "iNamePrismsNameFirstLowercased-EastAsian-South Korea": 5.134937092267437e-7,
    "iNamePrismsNameFirstLowercased-Muslim-Persian": 0.000013335124423711518,
    "iNamePrismsNameFirstLowercased-Muslim-Maghreb": 5.898090244919659e-10,
    "iNamePrismsNameFirstLowercased-Muslim-Nubian": 0.000001288664666440308,
    "iNamePrismsNameFirstLowercased-Muslim-ArabianPeninsula": 5.147868148621526e-7,
    "iNamePrismsNameFirstLowercased-European-SouthSlavs": 6.888054999540994e-7,
    "iNamePrismsNameFirstLowercased-European-Baltics": 4.5887837430488916e-7,
    "iNamePrismsNameFirstLowercased-European-French": 0.008008564463812727,
    "iNamePrismsNameFirstLowercased-European-Russian": 0.0000066528109505664696,
    "iNamePrismsNameFirstLowercased-European-EastEuropean": 0.0000018355974342669408,
    "iNamePrismsNameFirstLowercased-European-German": 0.016930560335513458
}