{
    "bUserExists": true,
    "bProfileIsPrivate": false,
    "bTooManyRequestsError": false,
    "sScrapedUrl": "https://profiles.udacity.com/u/amanda",
    "sScrapedUserId": "amanda",
    "sProfileLastUpdate": "Profile last updated 9 months ago",
    "sName": "Amanda",
    "sLocation": "San Diego, CA",
    "sEmail": "amanda.maureen21@gmail.com",
    "sStateOrCountry": "CA",
    "sImageUrl": "https://s3-us-west-2.amazonaws.com/udacity-profiles/production/photo/u1110007.jpg#1522530648725",
    "sLinkedInUrl": "https://www.linkedin.com/profile/view?id=103230458",
    "iDetailCount": 1,
    "iCountOfNanodegrees": 0,
    "iEducationCount": 0,
    "iExperienceCount": 0,
    "bPresentlyEmployed": false,
    "iAgeEstimate": null,
    "sLanguagesSpoken": "English, Spanish, Italian",
    "sImageOnGithubUrl": "https://raw.githubusercontent.com/Vandivier/data-science-practice/master/js/udacity-study/manually-scraped/profile-pics/amanda.jpg",
    "sInputLocation": "manually-scraped/broad-sample/amanda.txt",
    "sInputBaseName": "broad-sample",
    "sOutputDirectory": "manually-scraped/broad-sample - processed",
    "sOutputLocation": "manually-scraped/broad-sample - processed/amanda.json",
    "bNameTruncated": false,
    "sNameAsReported": "Amanda",
    "sNameWithoutSuffix": "Amanda",
    "sNameWithoutInitials": "Amanda",
    "sNameWithoutInitialsLowerCased": "amanda",
    "sNameFirst": "Amanda",
    "sNameFirstLowercased": "amanda",
    "oCachedData": {
        "bUserExists": true,
        "bProfileIsPrivate": false,
        "bTooManyRequestsError": false,
        "sScrapedUrl": "https://profiles.udacity.com/u/amanda",
        "sScrapedUserId": "amanda",
        "sProfileLastUpdate": "Profile last updated 9 months ago",
        "sName": "Amanda",
        "sLocation": "San Diego, CA",
        "sEmail": "amanda.maureen21@gmail.com",
        "sStateOrCountry": "CA",
        "sImageUrl": "https://s3-us-west-2.amazonaws.com/udacity-profiles/production/photo/u1110007.jpg#1522530648725",
        "sLinkedInUrl": "https://www.linkedin.com/profile/view?id=103230458",
        "iDetailCount": 1,
        "iCountOfNanodegrees": 0,
        "iEducationCount": 0,
        "iExperienceCount": 0,
        "bPresentlyEmployed": false,
        "iAgeEstimate": null,
        "sLanguagesSpoken": "English, Spanish, Italian",
        "sImageOnGithubUrl": "https://raw.githubusercontent.com/Vandivier/data-science-practice/master/js/udacity-study/manually-scraped/profile-pics/amanda.jpg",
        "sInputLocation": "manually-scraped/broad-sample/amanda.txt",
        "sInputBaseName": "broad-sample",
        "sOutputDirectory": "manually-scraped/broad-sample - processed",
        "sOutputLocation": "manually-scraped/broad-sample - processed/amanda.json",
        "bNameTruncated": false,
        "sNameAsReported": "Amanda",
        "sNameWithoutSuffix": "Amanda",
        "sNameWithoutInitials": "Amanda",
        "sNameFirst": "Amanda",
        "sNameFirstLowercased": "amanda",
        "bKairosImageSubmitted": true,
        "iKairosAge": 26,
        "iKairosAsian": 0.00293,
        "iKairosBlack": 0.00002,
        "iKairosMaleConfidence": 0.00002,
        "iKairosHispanic": 0.01897,
        "iKairosOtherEthnicity": 0.00114,
        "iKairosWhite": 0.97694,
        "iLanguagesSpoken": 3,
        "bSpeaksEnglish": true,
        "bSpeaksSpanish": true,
        "bSpeaksOther": true,
        "sState": "CA",
        "sCountry": "United States",
        "bGithubAccountClaimed": false,
        "bGitHubAccountFound": false,
        "bLinkedInAccountClaimed": false,
        "bLinkedInAccountFound": false,
        "iNamePrismsNameAsReportedTwoPrace": 0.0006690097239744591,
        "iNamePrismsNameAsReportedHispanic": 0.06332147130286253,
        "iNamePrismsNameAsReportedApi": 0.01337704563909264,
        "iNamePrismsNameAsReportedBlack": 0.02774648256479358,
        "iNamePrismsNameAsReportedAsian": 0.004874806522028931,
        "iNamePrismsNameAsReportedWhite": 0.8900111842472478,
        "iNamePrismsNameAsReported-Jewish": 3.6875824777853744e-8,
        "iNamePrismsNameAsReported-Nordic-Finland": 0.004004138246929796,
        "iNamePrismsNameAsReported-Greek": 9.219254518692692e-7,
        "iNamePrismsNameAsReported-SouthAsian": 0.00038631187943337884,
        "iNamePrismsNameAsReported-CelticEnglish": 0.1903702877777411,
        "iNamePrismsNameAsReported-Hispanic-Philippines": 0.000739961680032811,
        "iNamePrismsNameAsReported-Hispanic-Spanish": 0.008431450757068235,
        "iNamePrismsNameAsReported-Hispanic-Portuguese": 0.41290164090580833,
        "iNamePrismsNameAsReported-African-EastAfrican": 0.0007657878790199149,
        "iNamePrismsNameAsReported-African-WestAfrican": 0.007120668647431559,
        "iNamePrismsNameAsReported-African-SouthAfrican": 0.011103607349440318,
        "iNamePrismsNameAsReported-EastAsian-Japan": 1.0142507061344926e-7,
        "iNamePrismsNameAsReported-EastAsian-Chinese": 0.013478870623273322,
        "iNamePrismsNameAsReported-EastAsian-South Korea": 0.000023772340665750507,
        "iNamePrismsNameAsReported-Muslim-Persian": 0.00030217567360254116,
        "iNamePrismsNameAsReported-Muslim-Maghreb": 5.73808947741389e-8,
        "iNamePrismsNameAsReported-Muslim-Nubian": 0.000056684537234783733,
        "iNamePrismsNameAsReported-Muslim-ArabianPeninsula": 2.8680896724635336e-7,
        "iNamePrismsNameAsReported-European-SouthSlavs": 0.00014988181610256295,
        "iNamePrismsNameAsReported-European-Baltics": 0.002075191739819349,
        "iNamePrismsNameAsReported-European-French": 0.013120514060812712,
        "iNamePrismsNameAsReported-European-Russian": 9.288067243292549e-7,
        "iNamePrismsNameAsReported-European-EastEuropean": 0.0017089225159359802,
        "iNamePrismsNameAsReported-European-German": 0.0011226565575075172,
        "iNamePrismsNameWithoutSuffixTwoPrace": 0.0006690097239744591,
        "iNamePrismsNameWithoutSuffixHispanic": 0.06332147130286253,
        "iNamePrismsNameWithoutSuffixApi": 0.01337704563909264,
        "iNamePrismsNameWithoutSuffixBlack": 0.02774648256479358,
        "iNamePrismsNameWithoutSuffixAsian": 0.004874806522028931,
        "iNamePrismsNameWithoutSuffixWhite": 0.8900111842472478,
        "iNamePrismsNameWithoutSuffix-Jewish": 3.6875824777853744e-8,
        "iNamePrismsNameWithoutSuffix-Nordic-Finland": 0.004004138246929796,
        "iNamePrismsNameWithoutSuffix-Greek": 9.219254518692692e-7,
        "iNamePrismsNameWithoutSuffix-SouthAsian": 0.00038631187943337884,
        "iNamePrismsNameWithoutSuffix-CelticEnglish": 0.1903702877777411,
        "iNamePrismsNameWithoutSuffix-Hispanic-Philippines": 0.000739961680032811,
        "iNamePrismsNameWithoutSuffix-Hispanic-Spanish": 0.008431450757068235,
        "iNamePrismsNameWithoutSuffix-Hispanic-Portuguese": 0.41290164090580833,
        "iNamePrismsNameWithoutSuffix-African-EastAfrican": 0.0007657878790199149,
        "iNamePrismsNameWithoutSuffix-African-WestAfrican": 0.007120668647431559,
        "iNamePrismsNameWithoutSuffix-African-SouthAfrican": 0.011103607349440318,
        "iNamePrismsNameWithoutSuffix-EastAsian-Japan": 1.0142507061344926e-7,
        "iNamePrismsNameWithoutSuffix-EastAsian-Chinese": 0.013478870623273322,
        "iNamePrismsNameWithoutSuffix-EastAsian-South Korea": 0.000023772340665750507,
        "iNamePrismsNameWithoutSuffix-Muslim-Persian": 0.00030217567360254116,
        "iNamePrismsNameWithoutSuffix-Muslim-Maghreb": 5.73808947741389e-8,
        "iNamePrismsNameWithoutSuffix-Muslim-Nubian": 0.000056684537234783733,
        "iNamePrismsNameWithoutSuffix-Muslim-ArabianPeninsula": 2.8680896724635336e-7,
        "iNamePrismsNameWithoutSuffix-European-SouthSlavs": 0.00014988181610256295,
        "iNamePrismsNameWithoutSuffix-European-Baltics": 0.002075191739819349,
        "iNamePrismsNameWithoutSuffix-European-French": 0.013120514060812712,
        "iNamePrismsNameWithoutSuffix-European-Russian": 9.288067243292549e-7,
        "iNamePrismsNameWithoutSuffix-European-EastEuropean": 0.0017089225159359802,
        "iNamePrismsNameWithoutSuffix-European-German": 0.0011226565575075172,
        "iNamePrismsNameWithoutInitialsTwoPrace": 0.0006690097239744591,
        "iNamePrismsNameWithoutInitialsHispanic": 0.06332147130286253,
        "iNamePrismsNameWithoutInitialsApi": 0.01337704563909264,
        "iNamePrismsNameWithoutInitialsBlack": 0.02774648256479358,
        "iNamePrismsNameWithoutInitialsAsian": 0.004874806522028931,
        "iNamePrismsNameWithoutInitialsWhite": 0.8900111842472478,
        "iNamePrismsNameWithoutInitials-Jewish": 3.6875824777853744e-8,
        "iNamePrismsNameWithoutInitials-Nordic-Finland": 0.004004138246929796,
        "iNamePrismsNameWithoutInitials-Greek": 9.219254518692692e-7,
        "iNamePrismsNameWithoutInitials-SouthAsian": 0.00038631187943337884,
        "iNamePrismsNameWithoutInitials-CelticEnglish": 0.1903702877777411,
        "iNamePrismsNameWithoutInitials-Hispanic-Philippines": 0.000739961680032811,
        "iNamePrismsNameWithoutInitials-Hispanic-Spanish": 0.008431450757068235,
        "iNamePrismsNameWithoutInitials-Hispanic-Portuguese": 0.41290164090580833,
        "iNamePrismsNameWithoutInitials-African-EastAfrican": 0.0007657878790199149,
        "iNamePrismsNameWithoutInitials-African-WestAfrican": 0.007120668647431559,
        "iNamePrismsNameWithoutInitials-African-SouthAfrican": 0.011103607349440318,
        "iNamePrismsNameWithoutInitials-EastAsian-Japan": 1.0142507061344926e-7,
        "iNamePrismsNameWithoutInitials-EastAsian-Chinese": 0.013478870623273322,
        "iNamePrismsNameWithoutInitials-EastAsian-South Korea": 0.000023772340665750507,
        "iNamePrismsNameWithoutInitials-Muslim-Persian": 0.00030217567360254116,
        "iNamePrismsNameWithoutInitials-Muslim-Maghreb": 5.73808947741389e-8,
        "iNamePrismsNameWithoutInitials-Muslim-Nubian": 0.000056684537234783733,
        "iNamePrismsNameWithoutInitials-Muslim-ArabianPeninsula": 2.8680896724635336e-7,
        "iNamePrismsNameWithoutInitials-European-SouthSlavs": 0.00014988181610256295,
        "iNamePrismsNameWithoutInitials-European-Baltics": 0.002075191739819349,
        "iNamePrismsNameWithoutInitials-European-French": 0.013120514060812712,
        "iNamePrismsNameWithoutInitials-European-Russian": 9.288067243292549e-7,
        "iNamePrismsNameWithoutInitials-European-EastEuropean": 0.0017089225159359802,
        "iNamePrismsNameWithoutInitials-European-German": 0.0011226565575075172,
        "iNamePrismsNameFirstTwoPrace": 0.0006690097239744591,
        "iNamePrismsNameFirstHispanic": 0.06332147130286253,
        "iNamePrismsNameFirstApi": 0.01337704563909264,
        "iNamePrismsNameFirstBlack": 0.02774648256479358,
        "iNamePrismsNameFirstAsian": 0.004874806522028931,
        "iNamePrismsNameFirstWhite": 0.8900111842472478,
        "iNamePrismsNameFirst-Jewish": 3.6875824777853744e-8,
        "iNamePrismsNameFirst-Nordic-Finland": 0.004004138246929796,
        "iNamePrismsNameFirst-Greek": 9.219254518692692e-7,
        "iNamePrismsNameFirst-SouthAsian": 0.00038631187943337884,
        "iNamePrismsNameFirst-CelticEnglish": 0.1903702877777411,
        "iNamePrismsNameFirst-Hispanic-Philippines": 0.000739961680032811,
        "iNamePrismsNameFirst-Hispanic-Spanish": 0.008431450757068235,
        "iNamePrismsNameFirst-Hispanic-Portuguese": 0.41290164090580833,
        "iNamePrismsNameFirst-African-EastAfrican": 0.0007657878790199149,
        "iNamePrismsNameFirst-African-WestAfrican": 0.007120668647431559,
        "iNamePrismsNameFirst-African-SouthAfrican": 0.011103607349440318,
        "iNamePrismsNameFirst-EastAsian-Japan": 1.0142507061344926e-7,
        "iNamePrismsNameFirst-EastAsian-Chinese": 0.013478870623273322,
        "iNamePrismsNameFirst-EastAsian-South Korea": 0.000023772340665750507,
        "iNamePrismsNameFirst-Muslim-Persian": 0.00030217567360254116,
        "iNamePrismsNameFirst-Muslim-Maghreb": 5.73808947741389e-8,
        "iNamePrismsNameFirst-Muslim-Nubian": 0.000056684537234783733,
        "iNamePrismsNameFirst-Muslim-ArabianPeninsula": 2.8680896724635336e-7,
        "iNamePrismsNameFirst-European-SouthSlavs": 0.00014988181610256295,
        "iNamePrismsNameFirst-European-Baltics": 0.002075191739819349,
        "iNamePrismsNameFirst-European-French": 0.013120514060812712,
        "iNamePrismsNameFirst-European-Russian": 9.288067243292549e-7,
        "iNamePrismsNameFirst-European-EastEuropean": 0.0017089225159359802,
        "iNamePrismsNameFirst-European-German": 0.0011226565575075172,
        "iNamePrismsNameFirstLowercasedTwoPrace": 0.0006690097239744591,
        "iNamePrismsNameFirstLowercasedHispanic": 0.06332147130286253,
        "iNamePrismsNameFirstLowercasedApi": 0.01337704563909264,
        "iNamePrismsNameFirstLowercasedBlack": 0.02774648256479358,
        "iNamePrismsNameFirstLowercasedAsian": 0.004874806522028931,
        "iNamePrismsNameFirstLowercasedWhite": 0.8900111842472478,
        "iNamePrismsNameFirstLowercased-Jewish": 3.6875824777853744e-8,
        "iNamePrismsNameFirstLowercased-Nordic-Finland": 0.004004138246929796,
        "iNamePrismsNameFirstLowercased-Greek": 9.219254518692692e-7,
        "iNamePrismsNameFirstLowercased-SouthAsian": 0.00038631187943337884,
        "iNamePrismsNameFirstLowercased-CelticEnglish": 0.1903702877777411,
        "iNamePrismsNameFirstLowercased-Hispanic-Philippines": 0.000739961680032811,
        "iNamePrismsNameFirstLowercased-Hispanic-Spanish": 0.008431450757068235,
        "iNamePrismsNameFirstLowercased-Hispanic-Portuguese": 0.41290164090580833,
        "iNamePrismsNameFirstLowercased-African-EastAfrican": 0.0007657878790199149,
        "iNamePrismsNameFirstLowercased-African-WestAfrican": 0.007120668647431559,
        "iNamePrismsNameFirstLowercased-African-SouthAfrican": 0.011103607349440318,
        "iNamePrismsNameFirstLowercased-EastAsian-Japan": 1.0142507061344926e-7,
        "iNamePrismsNameFirstLowercased-EastAsian-Chinese": 0.013478870623273322,
        "iNamePrismsNameFirstLowercased-EastAsian-South Korea": 0.000023772340665750507,
        "iNamePrismsNameFirstLowercased-Muslim-Persian": 0.00030217567360254116,
        "iNamePrismsNameFirstLowercased-Muslim-Maghreb": 5.73808947741389e-8,
        "iNamePrismsNameFirstLowercased-Muslim-Nubian": 0.000056684537234783733,
        "iNamePrismsNameFirstLowercased-Muslim-ArabianPeninsula": 2.8680896724635336e-7,
        "iNamePrismsNameFirstLowercased-European-SouthSlavs": 0.00014988181610256295,
        "iNamePrismsNameFirstLowercased-European-Baltics": 0.002075191739819349,
        "iNamePrismsNameFirstLowercased-European-French": 0.013120514060812712,
        "iNamePrismsNameFirstLowercased-European-Russian": 9.288067243292549e-7,
        "iNamePrismsNameFirstLowercased-European-EastEuropean": 0.0017089225159359802,
        "iNamePrismsNameFirstLowercased-European-German": 0.0011226565575075172
    },
    "bKairosImageSubmitted": true,
    "iKairosAge": 26,
    "iKairosAsian": 0.00293,
    "iKairosBlack": 0.00002,
    "iKairosMaleConfidence": 0.00002,
    "iKairosHispanic": 0.01897,
    "iKairosOtherEthnicity": 0.00114,
    "iKairosWhite": 0.97694,
    "iLanguagesSpoken": 3,
    "bSpeaksEnglish": true,
    "bSpeaksSpanish": true,
    "bSpeaksOther": true,
    "sState": "CA",
    "sCountry": "United States",
    "bGithubAccountClaimed": false,
    "bGitHubAccountFound": false,
    "bLinkedInAccountClaimed": false,
    "bLinkedInAccountFound": false,
    "iNamePrismsNameAsReportedTwoPrace": 0.0006690097239744591,
    "iNamePrismsNameAsReportedHispanic": 0.06332147130286253,
    "iNamePrismsNameAsReportedApi": 0.01337704563909264,
    "iNamePrismsNameAsReportedBlack": 0.02774648256479358,
    "iNamePrismsNameAsReportedAsian": 0.004874806522028931,
    "iNamePrismsNameAsReportedWhite": 0.8900111842472478,
    "iNamePrismsNameAsReported-Jewish": 3.6875824777853744e-8,
    "iNamePrismsNameAsReported-Nordic-Finland": 0.004004138246929796,
    "iNamePrismsNameAsReported-Greek": 9.219254518692692e-7,
    "iNamePrismsNameAsReported-SouthAsian": 0.00038631187943337884,
    "iNamePrismsNameAsReported-CelticEnglish": 0.1903702877777411,
    "iNamePrismsNameAsReported-Hispanic-Philippines": 0.000739961680032811,
    "iNamePrismsNameAsReported-Hispanic-Spanish": 0.008431450757068235,
    "iNamePrismsNameAsReported-Hispanic-Portuguese": 0.41290164090580833,
    "iNamePrismsNameAsReported-African-EastAfrican": 0.0007657878790199149,
    "iNamePrismsNameAsReported-African-WestAfrican": 0.007120668647431559,
    "iNamePrismsNameAsReported-African-SouthAfrican": 0.011103607349440318,
    "iNamePrismsNameAsReported-EastAsian-Japan": 1.0142507061344926e-7,
    "iNamePrismsNameAsReported-EastAsian-Chinese": 0.013478870623273322,
    "iNamePrismsNameAsReported-EastAsian-South Korea": 0.000023772340665750507,
    "iNamePrismsNameAsReported-Muslim-Persian": 0.00030217567360254116,
    "iNamePrismsNameAsReported-Muslim-Maghreb": 5.73808947741389e-8,
    "iNamePrismsNameAsReported-Muslim-Nubian": 0.000056684537234783733,
    "iNamePrismsNameAsReported-Muslim-ArabianPeninsula": 2.8680896724635336e-7,
    "iNamePrismsNameAsReported-European-SouthSlavs": 0.00014988181610256295,
    "iNamePrismsNameAsReported-European-Baltics": 0.002075191739819349,
    "iNamePrismsNameAsReported-European-French": 0.013120514060812712,
    "iNamePrismsNameAsReported-European-Russian": 9.288067243292549e-7,
    "iNamePrismsNameAsReported-European-EastEuropean": 0.0017089225159359802,
    "iNamePrismsNameAsReported-European-German": 0.0011226565575075172,
    "iNamePrismsNameWithoutSuffixTwoPrace": 0.0006690097239744591,
    "iNamePrismsNameWithoutSuffixHispanic": 0.06332147130286253,
    "iNamePrismsNameWithoutSuffixApi": 0.01337704563909264,
    "iNamePrismsNameWithoutSuffixBlack": 0.02774648256479358,
    "iNamePrismsNameWithoutSuffixAsian": 0.004874806522028931,
    "iNamePrismsNameWithoutSuffixWhite": 0.8900111842472478,
    "iNamePrismsNameWithoutSuffix-Jewish": 3.6875824777853744e-8,
    "iNamePrismsNameWithoutSuffix-Nordic-Finland": 0.004004138246929796,
    "iNamePrismsNameWithoutSuffix-Greek": 9.219254518692692e-7,
    "iNamePrismsNameWithoutSuffix-SouthAsian": 0.00038631187943337884,
    "iNamePrismsNameWithoutSuffix-CelticEnglish": 0.1903702877777411,
    "iNamePrismsNameWithoutSuffix-Hispanic-Philippines": 0.000739961680032811,
    "iNamePrismsNameWithoutSuffix-Hispanic-Spanish": 0.008431450757068235,
    "iNamePrismsNameWithoutSuffix-Hispanic-Portuguese": 0.41290164090580833,
    "iNamePrismsNameWithoutSuffix-African-EastAfrican": 0.0007657878790199149,
    "iNamePrismsNameWithoutSuffix-African-WestAfrican": 0.007120668647431559,
    "iNamePrismsNameWithoutSuffix-African-SouthAfrican": 0.011103607349440318,
    "iNamePrismsNameWithoutSuffix-EastAsian-Japan": 1.0142507061344926e-7,
    "iNamePrismsNameWithoutSuffix-EastAsian-Chinese": 0.013478870623273322,
    "iNamePrismsNameWithoutSuffix-EastAsian-South Korea": 0.000023772340665750507,
    "iNamePrismsNameWithoutSuffix-Muslim-Persian": 0.00030217567360254116,
    "iNamePrismsNameWithoutSuffix-Muslim-Maghreb": 5.73808947741389e-8,
    "iNamePrismsNameWithoutSuffix-Muslim-Nubian": 0.000056684537234783733,
    "iNamePrismsNameWithoutSuffix-Muslim-ArabianPeninsula": 2.8680896724635336e-7,
    "iNamePrismsNameWithoutSuffix-European-SouthSlavs": 0.00014988181610256295,
    "iNamePrismsNameWithoutSuffix-European-Baltics": 0.002075191739819349,
    "iNamePrismsNameWithoutSuffix-European-French": 0.013120514060812712,
    "iNamePrismsNameWithoutSuffix-European-Russian": 9.288067243292549e-7,
    "iNamePrismsNameWithoutSuffix-European-EastEuropean": 0.0017089225159359802,
    "iNamePrismsNameWithoutSuffix-European-German": 0.0011226565575075172,
    "iNamePrismsNameWithoutInitialsTwoPrace": 0.0006690097239744591,
    "iNamePrismsNameWithoutInitialsHispanic": 0.06332147130286253,
    "iNamePrismsNameWithoutInitialsApi": 0.01337704563909264,
    "iNamePrismsNameWithoutInitialsBlack": 0.02774648256479358,
    "iNamePrismsNameWithoutInitialsAsian": 0.004874806522028931,
    "iNamePrismsNameWithoutInitialsWhite": 0.8900111842472478,
    "iNamePrismsNameWithoutInitials-Jewish": 3.6875824777853744e-8,
    "iNamePrismsNameWithoutInitials-Nordic-Finland": 0.004004138246929796,
    "iNamePrismsNameWithoutInitials-Greek": 9.219254518692692e-7,
    "iNamePrismsNameWithoutInitials-SouthAsian": 0.00038631187943337884,
    "iNamePrismsNameWithoutInitials-CelticEnglish": 0.1903702877777411,
    "iNamePrismsNameWithoutInitials-Hispanic-Philippines": 0.000739961680032811,
    "iNamePrismsNameWithoutInitials-Hispanic-Spanish": 0.008431450757068235,
    "iNamePrismsNameWithoutInitials-Hispanic-Portuguese": 0.41290164090580833,
    "iNamePrismsNameWithoutInitials-African-EastAfrican": 0.0007657878790199149,
    "iNamePrismsNameWithoutInitials-African-WestAfrican": 0.007120668647431559,
    "iNamePrismsNameWithoutInitials-African-SouthAfrican": 0.011103607349440318,
    "iNamePrismsNameWithoutInitials-EastAsian-Japan": 1.0142507061344926e-7,
    "iNamePrismsNameWithoutInitials-EastAsian-Chinese": 0.013478870623273322,
    "iNamePrismsNameWithoutInitials-EastAsian-South Korea": 0.000023772340665750507,
    "iNamePrismsNameWithoutInitials-Muslim-Persian": 0.00030217567360254116,
    "iNamePrismsNameWithoutInitials-Muslim-Maghreb": 5.73808947741389e-8,
    "iNamePrismsNameWithoutInitials-Muslim-Nubian": 0.000056684537234783733,
    "iNamePrismsNameWithoutInitials-Muslim-ArabianPeninsula": 2.8680896724635336e-7,
    "iNamePrismsNameWithoutInitials-European-SouthSlavs": 0.00014988181610256295,
    "iNamePrismsNameWithoutInitials-European-Baltics": 0.002075191739819349,
    "iNamePrismsNameWithoutInitials-European-French": 0.013120514060812712,
    "iNamePrismsNameWithoutInitials-European-Russian": 9.288067243292549e-7,
    "iNamePrismsNameWithoutInitials-European-EastEuropean": 0.0017089225159359802,
    "iNamePrismsNameWithoutInitials-European-German": 0.0011226565575075172,
    "iNamePrismsNameWithoutInitialsLowerCasedTwoPrace": 0.0006690097239744591,
    "iNamePrismsNameWithoutInitialsLowerCasedHispanic": 0.06332147130286253,
    "iNamePrismsNameWithoutInitialsLowerCasedApi": 0.01337704563909264,
    "iNamePrismsNameWithoutInitialsLowerCasedBlack": 0.02774648256479358,
    "iNamePrismsNameWithoutInitialsLowerCasedAsian": 0.004874806522028931,
    "iNamePrismsNameWithoutInitialsLowerCasedWhite": 0.8900111842472478,
    "iNamePrismsNameWithoutInitialsLowerCased-Jewish": 3.6875824777853744e-8,
    "iNamePrismsNameWithoutInitialsLowerCased-Nordic-Finland": 0.004004138246929796,
    "iNamePrismsNameWithoutInitialsLowerCased-Greek": 9.219254518692692e-7,
    "iNamePrismsNameWithoutInitialsLowerCased-SouthAsian": 0.00038631187943337884,
    "iNamePrismsNameWithoutInitialsLowerCased-CelticEnglish": 0.1903702877777411,
    "iNamePrismsNameWithoutInitialsLowerCased-Hispanic-Philippines": 0.000739961680032811,
    "iNamePrismsNameWithoutInitialsLowerCased-Hispanic-Spanish": 0.008431450757068235,
    "iNamePrismsNameWithoutInitialsLowerCased-Hispanic-Portuguese": 0.41290164090580833,
    "iNamePrismsNameWithoutInitialsLowerCased-African-EastAfrican": 0.0007657878790199149,
    "iNamePrismsNameWithoutInitialsLowerCased-African-WestAfrican": 0.007120668647431559,
    "iNamePrismsNameWithoutInitialsLowerCased-African-SouthAfrican": 0.011103607349440318,
    "iNamePrismsNameWithoutInitialsLowerCased-EastAsian-Japan": 1.0142507061344926e-7,
    "iNamePrismsNameWithoutInitialsLowerCased-EastAsian-Chinese": 0.013478870623273322,
    "iNamePrismsNameWithoutInitialsLowerCased-EastAsian-South Korea": 0.000023772340665750507,
    "iNamePrismsNameWithoutInitialsLowerCased-Muslim-Persian": 0.00030217567360254116,
    "iNamePrismsNameWithoutInitialsLowerCased-Muslim-Maghreb": 5.73808947741389e-8,
    "iNamePrismsNameWithoutInitialsLowerCased-Muslim-Nubian": 0.000056684537234783733,
    "iNamePrismsNameWithoutInitialsLowerCased-Muslim-ArabianPeninsula": 2.8680896724635336e-7,
    "iNamePrismsNameWithoutInitialsLowerCased-European-SouthSlavs": 0.00014988181610256295,
    "iNamePrismsNameWithoutInitialsLowerCased-European-Baltics": 0.002075191739819349,
    "iNamePrismsNameWithoutInitialsLowerCased-European-French": 0.013120514060812712,
    "iNamePrismsNameWithoutInitialsLowerCased-European-Russian": 9.288067243292549e-7,
    "iNamePrismsNameWithoutInitialsLowerCased-European-EastEuropean": 0.0017089225159359802,
    "iNamePrismsNameWithoutInitialsLowerCased-European-German": 0.0011226565575075172,
    "iNamePrismsNameFirstTwoPrace": 0.0006690097239744591,
    "iNamePrismsNameFirstHispanic": 0.06332147130286253,
    "iNamePrismsNameFirstApi": 0.01337704563909264,
    "iNamePrismsNameFirstBlack": 0.02774648256479358,
    "iNamePrismsNameFirstAsian": 0.004874806522028931,
    "iNamePrismsNameFirstWhite": 0.8900111842472478,
    "iNamePrismsNameFirst-Jewish": 3.6875824777853744e-8,
    "iNamePrismsNameFirst-Nordic-Finland": 0.004004138246929796,
    "iNamePrismsNameFirst-Greek": 9.219254518692692e-7,
    "iNamePrismsNameFirst-SouthAsian": 0.00038631187943337884,
    "iNamePrismsNameFirst-CelticEnglish": 0.1903702877777411,
    "iNamePrismsNameFirst-Hispanic-Philippines": 0.000739961680032811,
    "iNamePrismsNameFirst-Hispanic-Spanish": 0.008431450757068235,
    "iNamePrismsNameFirst-Hispanic-Portuguese": 0.41290164090580833,
    "iNamePrismsNameFirst-African-EastAfrican": 0.0007657878790199149,
    "iNamePrismsNameFirst-African-WestAfrican": 0.007120668647431559,
    "iNamePrismsNameFirst-African-SouthAfrican": 0.011103607349440318,
    "iNamePrismsNameFirst-EastAsian-Japan": 1.0142507061344926e-7,
    "iNamePrismsNameFirst-EastAsian-Chinese": 0.013478870623273322,
    "iNamePrismsNameFirst-EastAsian-South Korea": 0.000023772340665750507,
    "iNamePrismsNameFirst-Muslim-Persian": 0.00030217567360254116,
    "iNamePrismsNameFirst-Muslim-Maghreb": 5.73808947741389e-8,
    "iNamePrismsNameFirst-Muslim-Nubian": 0.000056684537234783733,
    "iNamePrismsNameFirst-Muslim-ArabianPeninsula": 2.8680896724635336e-7,
    "iNamePrismsNameFirst-European-SouthSlavs": 0.00014988181610256295,
    "iNamePrismsNameFirst-European-Baltics": 0.002075191739819349,
    "iNamePrismsNameFirst-European-French": 0.013120514060812712,
    "iNamePrismsNameFirst-European-Russian": 9.288067243292549e-7,
    "iNamePrismsNameFirst-European-EastEuropean": 0.0017089225159359802,
    "iNamePrismsNameFirst-European-German": 0.0011226565575075172,
    "iNamePrismsNameFirstLowercasedTwoPrace": 0.0006690097239744591,
    "iNamePrismsNameFirstLowercasedHispanic": 0.06332147130286253,
    "iNamePrismsNameFirstLowercasedApi": 0.01337704563909264,
    "iNamePrismsNameFirstLowercasedBlack": 0.02774648256479358,
    "iNamePrismsNameFirstLowercasedAsian": 0.004874806522028931,
    "iNamePrismsNameFirstLowercasedWhite": 0.8900111842472478,
    "iNamePrismsNameFirstLowercased-Jewish": 3.6875824777853744e-8,
    "iNamePrismsNameFirstLowercased-Nordic-Finland": 0.004004138246929796,
    "iNamePrismsNameFirstLowercased-Greek": 9.219254518692692e-7,
    "iNamePrismsNameFirstLowercased-SouthAsian": 0.00038631187943337884,
    "iNamePrismsNameFirstLowercased-CelticEnglish": 0.1903702877777411,
    "iNamePrismsNameFirstLowercased-Hispanic-Philippines": 0.000739961680032811,
    "iNamePrismsNameFirstLowercased-Hispanic-Spanish": 0.008431450757068235,
    "iNamePrismsNameFirstLowercased-Hispanic-Portuguese": 0.41290164090580833,
    "iNamePrismsNameFirstLowercased-African-EastAfrican": 0.0007657878790199149,
    "iNamePrismsNameFirstLowercased-African-WestAfrican": 0.007120668647431559,
    "iNamePrismsNameFirstLowercased-African-SouthAfrican": 0.011103607349440318,
    "iNamePrismsNameFirstLowercased-EastAsian-Japan": 1.0142507061344926e-7,
    "iNamePrismsNameFirstLowercased-EastAsian-Chinese": 0.013478870623273322,
    "iNamePrismsNameFirstLowercased-EastAsian-South Korea": 0.000023772340665750507,
    "iNamePrismsNameFirstLowercased-Muslim-Persian": 0.00030217567360254116,
    "iNamePrismsNameFirstLowercased-Muslim-Maghreb": 5.73808947741389e-8,
    "iNamePrismsNameFirstLowercased-Muslim-Nubian": 0.000056684537234783733,
    "iNamePrismsNameFirstLowercased-Muslim-ArabianPeninsula": 2.8680896724635336e-7,
    "iNamePrismsNameFirstLowercased-European-SouthSlavs": 0.00014988181610256295,
    "iNamePrismsNameFirstLowercased-European-Baltics": 0.002075191739819349,
    "iNamePrismsNameFirstLowercased-European-French": 0.013120514060812712,
    "iNamePrismsNameFirstLowercased-European-Russian": 9.288067243292549e-7,
    "iNamePrismsNameFirstLowercased-European-EastEuropean": 0.0017089225159359802,
    "iNamePrismsNameFirstLowercased-European-German": 0.0011226565575075172
}