{
    "bUserExists": true,
    "bProfileIsPrivate": false,
    "bTooManyRequestsError": false,
    "sScrapedUrl": "https://profiles.udacity.com/u/jonathan24",
    "sScrapedUserId": "jonathan24",
    "sProfileLastUpdate": "Profile last updated 9 months ago",
    "sName": "Jonathan",
    "sLocation": "Westborough, MA",
    "sEmail": "jmstickney@gmail.com",
    "sStateOrCountry": "MA",
    "sImageUrl": "https://s3-us-west-2.amazonaws.com/udacity-profiles/production/photo/u11764518.jpg#1522545640533",
    "sLinkedInUrl": "https://www.linkedin.com/in/jmstickney",
    "iDetailCount": 1,
    "iCountOfNanodegrees": 0,
    "iEducationCount": 0,
    "iExperienceCount": 0,
    "bPresentlyEmployed": false,
    "iAgeEstimate": null,
    "sLanguagesSpoken": "English",
    "sImageOnGithubUrl": "https://raw.githubusercontent.com/Vandivier/data-science-practice/master/js/udacity-study/manually-scraped/profile-pics/jonathan24.jpg",
    "sInputLocation": "manually-scraped/broad-sample/jonathan24.txt",
    "sInputBaseName": "broad-sample",
    "sOutputDirectory": "manually-scraped/broad-sample - processed",
    "sOutputLocation": "manually-scraped/broad-sample - processed/jonathan24.json",
    "bNameTruncated": false,
    "sNameAsReported": "Jonathan",
    "sNameWithoutSuffix": "Jonathan",
    "sNameWithoutInitials": "Jonathan",
    "sNameFirst": "Jonathan",
    "sNameFirstLowercased": "jonathan",
    "oCachedData": {
        "bUserExists": true,
        "bProfileIsPrivate": false,
        "bTooManyRequestsError": false,
        "sScrapedUrl": "https://profiles.udacity.com/u/jonathan24",
        "sScrapedUserId": "jonathan24",
        "sProfileLastUpdate": "Profile last updated 9 months ago",
        "sName": "Jonathan",
        "sLocation": "Westborough, MA",
        "sEmail": "jmstickney@gmail.com",
        "sStateOrCountry": "MA",
        "sImageUrl": "https://s3-us-west-2.amazonaws.com/udacity-profiles/production/photo/u11764518.jpg#1522545640533",
        "sLinkedInUrl": "https://www.linkedin.com/in/jmstickney",
        "iDetailCount": 1,
        "iCountOfNanodegrees": 0,
        "iEducationCount": 0,
        "iExperienceCount": 0,
        "bPresentlyEmployed": false,
        "iAgeEstimate": null,
        "sLanguagesSpoken": "English",
        "sImageOnGithubUrl": "https://raw.githubusercontent.com/Vandivier/data-science-practice/master/js/udacity-study/manually-scraped/profile-pics/jonathan24.jpg",
        "sInputLocation": "manually-scraped/broad-sample/jonathan24.txt",
        "sInputBaseName": "broad-sample",
        "sOutputDirectory": "manually-scraped/broad-sample - processed",
        "sOutputLocation": "manually-scraped/broad-sample - processed/jonathan24.json",
        "bNameTruncated": false,
        "sNameAsReported": "Jonathan",
        "sNameWithoutSuffix": "Jonathan",
        "sNameWithoutInitials": "Jonathan",
        "sNameFirst": "Jonathan",
        "sNameFirstLowercased": "jonathan",
        "oCachedData": {
            "bUserExists": true,
            "bProfileIsPrivate": false,
            "bTooManyRequestsError": false,
            "sScrapedUrl": "https://profiles.udacity.com/u/jonathan24",
            "sScrapedUserId": "jonathan24",
            "sProfileLastUpdate": "Profile last updated 9 months ago",
            "sName": "Jonathan",
            "sLocation": "Westborough, MA",
            "sEmail": "jmstickney@gmail.com",
            "sStateOrCountry": "MA",
            "sImageUrl": "https://s3-us-west-2.amazonaws.com/udacity-profiles/production/photo/u11764518.jpg#1522545640533",
            "sLinkedInUrl": "https://www.linkedin.com/in/jmstickney",
            "iDetailCount": 1,
            "iCountOfNanodegrees": 0,
            "iEducationCount": 0,
            "iExperienceCount": 0,
            "bPresentlyEmployed": false,
            "iAgeEstimate": null,
            "sLanguagesSpoken": "English",
            "sImageOnGithubUrl": "https://raw.githubusercontent.com/Vandivier/data-science-practice/master/js/udacity-study/manually-scraped/profile-pics/jonathan24.jpg",
            "sInputLocation": "manually-scraped/broad-sample/jonathan24.txt",
            "sInputBaseName": "broad-sample",
            "sOutputDirectory": "manually-scraped/broad-sample - processed",
            "sOutputLocation": "manually-scraped/broad-sample - processed/jonathan24.json",
            "bNameTruncated": false,
            "sNameAsReported": "Jonathan",
            "sNameWithoutSuffix": "Jonathan",
            "sNameWithoutInitials": "Jonathan",
            "sNameFirst": "Jonathan",
            "sNameFirstLowercased": "jonathan",
            "oCachedData": {
                "bUserExists": true,
                "bProfileIsPrivate": false,
                "bTooManyRequestsError": false,
                "sScrapedUrl": "https://profiles.udacity.com/u/jonathan24",
                "sScrapedUserId": "jonathan24",
                "sProfileLastUpdate": "Profile last updated 9 months ago",
                "sName": "Jonathan",
                "sLocation": "Westborough, MA",
                "sEmail": "jmstickney@gmail.com",
                "sStateOrCountry": "MA",
                "sImageUrl": "https://s3-us-west-2.amazonaws.com/udacity-profiles/production/photo/u11764518.jpg#1522545640533",
                "sLinkedInUrl": "https://www.linkedin.com/in/jmstickney",
                "iDetailCount": 1,
                "iCountOfNanodegrees": 0,
                "iEducationCount": 0,
                "iExperienceCount": 0,
                "bPresentlyEmployed": false,
                "iAgeEstimate": null,
                "sLanguagesSpoken": "English",
                "sImageOnGithubUrl": "https://raw.githubusercontent.com/Vandivier/data-science-practice/master/js/udacity-study/manually-scraped/profile-pics/jonathan24.jpg",
                "sInputLocation": "manually-scraped/broad-sample/jonathan24.txt",
                "sInputBaseName": "broad-sample",
                "sOutputDirectory": "manually-scraped/broad-sample - processed",
                "sOutputLocation": "manually-scraped/broad-sample - processed/jonathan24.json",
                "bNameTruncated": false,
                "sNameAsReported": "Jonathan",
                "sNameWithoutSuffix": "Jonathan",
                "sNameWithoutInitials": "Jonathan",
                "sNameFirst": "Jonathan",
                "sNameFirstLowercased": "jonathan",
                "oCachedData": {
                    "bUserExists": true,
                    "bProfileIsPrivate": false,
                    "bTooManyRequestsError": false,
                    "sScrapedUrl": "https://profiles.udacity.com/u/jonathan24",
                    "sScrapedUserId": "jonathan24",
                    "sProfileLastUpdate": "Profile last updated 9 months ago",
                    "sName": "Jonathan",
                    "sLocation": "Westborough, MA",
                    "sEmail": "jmstickney@gmail.com",
                    "sStateOrCountry": "MA",
                    "sImageUrl": "https://s3-us-west-2.amazonaws.com/udacity-profiles/production/photo/u11764518.jpg#1522545640533",
                    "sLinkedInUrl": "https://www.linkedin.com/in/jmstickney",
                    "iDetailCount": 1,
                    "iCountOfNanodegrees": 0,
                    "iEducationCount": 0,
                    "iExperienceCount": 0,
                    "bPresentlyEmployed": false,
                    "iAgeEstimate": null,
                    "sLanguagesSpoken": "English",
                    "sImageOnGithubUrl": "https://raw.githubusercontent.com/Vandivier/data-science-practice/master/js/udacity-study/manually-scraped/profile-pics/jonathan24.jpg",
                    "sInputLocation": "manually-scraped/broad-sample/jonathan24.txt",
                    "sInputBaseName": "broad-sample",
                    "sOutputDirectory": "manually-scraped/broad-sample - processed",
                    "sOutputLocation": "manually-scraped/broad-sample - processed/jonathan24.json",
                    "bNameTruncated": false,
                    "sNameAsReported": "Jonathan",
                    "sNameWithoutSuffix": "Jonathan",
                    "sNameWithoutInitials": "Jonathan",
                    "sNameFirst": "Jonathan",
                    "oCachedData": {
                        "bUserExists": true,
                        "bProfileIsPrivate": false,
                        "bTooManyRequestsError": false,
                        "sScrapedUrl": "https://profiles.udacity.com/u/jonathan24",
                        "sScrapedUserId": "jonathan24",
                        "sProfileLastUpdate": "Profile last updated 9 months ago",
                        "sName": "Jonathan",
                        "sLocation": "Westborough, MA",
                        "sEmail": "jmstickney@gmail.com",
                        "sStateOrCountry": "MA",
                        "sImageUrl": "https://s3-us-west-2.amazonaws.com/udacity-profiles/production/photo/u11764518.jpg#1522545640533",
                        "sLinkedInUrl": "https://www.linkedin.com/in/jmstickney",
                        "iDetailCount": 1,
                        "iCountOfNanodegrees": 0,
                        "iEducationCount": 0,
                        "iExperienceCount": 0,
                        "bPresentlyEmployed": false,
                        "iAgeEstimate": null,
                        "sLanguagesSpoken": "English",
                        "sImageOnGithubUrl": "https://raw.githubusercontent.com/Vandivier/data-science-practice/master/js/udacity-study/manually-scraped/profile-pics/jonathan24.jpg",
                        "sInputLocation": "manually-scraped/broad-sample/jonathan24.txt",
                        "sInputBaseName": "broad-sample",
                        "sOutputDirectory": "manually-scraped/broad-sample - processed",
                        "sOutputLocation": "manually-scraped/broad-sample - processed/jonathan24.json",
                        "bNameTruncated": false,
                        "sNameAsReported": "Jonathan",
                        "sNameWithoutSuffix": "Jonathan",
                        "sNameWithoutInitials": "Jonathan",
                        "sNameFirst": "Jonathan",
                        "oCachedData": {
                            "bUserExists": true,
                            "bProfileIsPrivate": false,
                            "bTooManyRequestsError": false,
                            "sScrapedUrl": "https://profiles.udacity.com/u/jonathan24",
                            "sScrapedUserId": "jonathan24",
                            "sProfileLastUpdate": "Profile last updated 9 months ago",
                            "sName": "Jonathan",
                            "sLocation": "Westborough, MA",
                            "sEmail": "jmstickney@gmail.com",
                            "sStateOrCountry": "MA",
                            "sImageUrl": "https://s3-us-west-2.amazonaws.com/udacity-profiles/production/photo/u11764518.jpg#1522545640533",
                            "sLinkedInUrl": "https://www.linkedin.com/in/jmstickney",
                            "iDetailCount": 1,
                            "iCountOfNanodegrees": 0,
                            "iEducationCount": 0,
                            "iExperienceCount": 0,
                            "bPresentlyEmployed": false,
                            "iAgeEstimate": null,
                            "sLanguagesSpoken": "English",
                            "sImageOnGithubUrl": "https://raw.githubusercontent.com/Vandivier/data-science-practice/master/js/udacity-study/manually-scraped/profile-pics/jonathan24.jpg",
                            "sInputLocation": "manually-scraped/broad-sample/jonathan24.txt",
                            "sInputBaseName": "broad-sample",
                            "sOutputDirectory": "manually-scraped/broad-sample - processed",
                            "sOutputLocation": "manually-scraped/broad-sample - processed/jonathan24.json",
                            "bNameTruncated": false,
                            "sNameAsReported": "Jonathan",
                            "sNameWithoutSuffix": "Jonathan",
                            "sNameWithoutInitials": "Jonathan",
                            "sFirstName": "Jonathan",
                            "oCachedData": {
                                "bUserExists": true,
                                "bProfileIsPrivate": false,
                                "bTooManyRequestsError": false,
                                "sScrapedUrl": "https://profiles.udacity.com/u/jonathan24",
                                "sScrapedUserId": "jonathan24",
                                "sProfileLastUpdate": "Profile last updated 9 months ago",
                                "sName": "Jonathan",
                                "sLocation": "Westborough, MA",
                                "sEmail": "jmstickney@gmail.com",
                                "sStateOrCountry": "MA",
                                "sImageUrl": "https://s3-us-west-2.amazonaws.com/udacity-profiles/production/photo/u11764518.jpg#1522545640533",
                                "sLinkedInUrl": "https://www.linkedin.com/in/jmstickney",
                                "iDetailCount": 1,
                                "iCountOfNanodegrees": 0,
                                "iEducationCount": 0,
                                "iExperienceCount": 0,
                                "bPresentlyEmployed": false,
                                "iAgeEstimate": null,
                                "sLanguagesSpoken": "English",
                                "sImageOnGithubUrl": "https://raw.githubusercontent.com/Vandivier/data-science-practice/master/js/udacity-study/manually-scraped/profile-pics/jonathan24.jpg",
                                "sInputLocation": "manually-scraped/broad-sample/jonathan24.txt",
                                "sInputBaseName": "broad-sample",
                                "sOutputDirectory": "manually-scraped/broad-sample - processed",
                                "sOutputLocation": "manually-scraped/broad-sample - processed/jonathan24.json",
                                "bKairosImageSubmitted": true,
                                "iKairosAge": 33,
                                "iKairosAsian": 0.00474,
                                "iKairosBlack": 0.01112,
                                "iKairosMaleConfidence": 0.99999,
                                "iKairosHispanic": 0.042,
                                "iKairosOtherEthnicity": 0.00805,
                                "iKairosWhite": 0.93408,
                                "bNameTruncated": false,
                                "iLanguagesSpoken": 1,
                                "bSpeaksEnglish": true,
                                "bSpeaksSpanish": false,
                                "bSpeaksOther": false,
                                "sState": "MA",
                                "sCountry": "United States",
                                "bGithubAccountClaimed": false,
                                "bGitHubAccountFound": false
                            },
                            "bKairosImageSubmitted": true,
                            "iKairosAge": 33,
                            "iKairosAsian": 0.00474,
                            "iKairosBlack": 0.01112,
                            "iKairosMaleConfidence": 0.99999,
                            "iKairosHispanic": 0.042,
                            "iKairosOtherEthnicity": 0.00805,
                            "iKairosWhite": 0.93408,
                            "iLanguagesSpoken": 1,
                            "bSpeaksEnglish": true,
                            "bSpeaksSpanish": false,
                            "bSpeaksOther": false,
                            "sState": "MA",
                            "sCountry": "United States",
                            "bGithubAccountClaimed": false,
                            "bGitHubAccountFound": false
                        },
                        "bKairosImageSubmitted": true,
                        "iKairosAge": 33,
                        "iKairosAsian": 0.00474,
                        "iKairosBlack": 0.01112,
                        "iKairosMaleConfidence": 0.99999,
                        "iKairosHispanic": 0.042,
                        "iKairosOtherEthnicity": 0.00805,
                        "iKairosWhite": 0.93408,
                        "iLanguagesSpoken": 1,
                        "bSpeaksEnglish": true,
                        "bSpeaksSpanish": false,
                        "bSpeaksOther": false,
                        "sState": "MA",
                        "sCountry": "United States",
                        "bGithubAccountClaimed": false,
                        "bGitHubAccountFound": false
                    },
                    "bKairosImageSubmitted": true,
                    "iKairosAge": 33,
                    "iKairosAsian": 0.00474,
                    "iKairosBlack": 0.01112,
                    "iKairosMaleConfidence": 0.99999,
                    "iKairosHispanic": 0.042,
                    "iKairosOtherEthnicity": 0.00805,
                    "iKairosWhite": 0.93408,
                    "iLanguagesSpoken": 1,
                    "bSpeaksEnglish": true,
                    "bSpeaksSpanish": false,
                    "bSpeaksOther": false,
                    "sState": "MA",
                    "sCountry": "United States",
                    "bGithubAccountClaimed": false,
                    "bGitHubAccountFound": false
                },
                "bKairosImageSubmitted": true,
                "iKairosAge": 33,
                "iKairosAsian": 0.00474,
                "iKairosBlack": 0.01112,
                "iKairosMaleConfidence": 0.99999,
                "iKairosHispanic": 0.042,
                "iKairosOtherEthnicity": 0.00805,
                "iKairosWhite": 0.93408,
                "iLanguagesSpoken": 1,
                "bSpeaksEnglish": true,
                "bSpeaksSpanish": false,
                "bSpeaksOther": false,
                "sState": "MA",
                "sCountry": "United States",
                "bGithubAccountClaimed": false,
                "bGitHubAccountFound": false
            },
            "bKairosImageSubmitted": true,
            "iKairosAge": 33,
            "iKairosAsian": 0.00474,
            "iKairosBlack": 0.01112,
            "iKairosMaleConfidence": 0.99999,
            "iKairosHispanic": 0.042,
            "iKairosOtherEthnicity": 0.00805,
            "iKairosWhite": 0.93408,
            "iLanguagesSpoken": 1,
            "bSpeaksEnglish": true,
            "bSpeaksSpanish": false,
            "bSpeaksOther": false,
            "sState": "MA",
            "sCountry": "United States",
            "bGithubAccountClaimed": false,
            "bGitHubAccountFound": false,
            "bLinkedInAccountClaimed": true,
            "bLinkedInAccountFound": true,
            "iLinkedInConnections": "500+",
            "sLinkedInFullName": "Jonathan Stickney",
            "sLinkedInPath": "jmstickney",
            "sLinkedInImageUrl": "https://media.licdn.com/dms/image/C4D03AQFDu6vkxUwIPQ/profile-displayphoto-shrink_800_800/0?e=1529654400&v=beta&t=gtC4w_8CNBMqm07HZIyxMlJ899ckjC4wKPfKRoc9www",
            "sPossibleLinkedInEmailAddress": "",
            "iLinkedInAccomplishments": 0,
            "iCertifications": "",
            "iLinkedInExperience": 7,
            "iLinkedInEducation": 2,
            "bLinkedInCurrentlyEmployed": true,
            "iFlatIronExperience": 0,
            "iGeneralAssemblyExperience": 0,
            "iUdacityExperience": 0,
            "iCourseraExperience": 0,
            "iUdemyExperience": 0,
            "iAppAcademyExperience": 0,
            "iFlatIronCredentials": 0,
            "iGeneralAssemblyCredentials": 0,
            "iUdacityCredentials": 0,
            "iCourseraCredentials": 0,
            "iUdemyCredentials": 0,
            "iAppAcademyCredentials": 0,
            "iAlternativeCredentialCount": 0,
            "bIsAlternativelyEducated": false,
            "iAlternativeExperienceCount": 0,
            "bIsAlternativelyExperienced": false
        },
        "bKairosImageSubmitted": true,
        "iKairosAge": 33,
        "iKairosAsian": 0.00474,
        "iKairosBlack": 0.01112,
        "iKairosMaleConfidence": 0.99999,
        "iKairosHispanic": 0.042,
        "iKairosOtherEthnicity": 0.00805,
        "iKairosWhite": 0.93408,
        "iLanguagesSpoken": 1,
        "bSpeaksEnglish": true,
        "bSpeaksSpanish": false,
        "bSpeaksOther": false,
        "sState": "MA",
        "sCountry": "United States",
        "bGithubAccountClaimed": false,
        "bGitHubAccountFound": false,
        "bLinkedInAccountClaimed": true,
        "bLinkedInAccountFound": true,
        "sLinkedInFullName": "Jonathan Stickney",
        "sLinkedInPath": "jmstickney",
        "sLinkedInImageUrl": "https://media.licdn.com/dms/image/C4D03AQFDu6vkxUwIPQ/profile-displayphoto-shrink_800_800/0?e=1529654400&v=beta&t=gtC4w_8CNBMqm07HZIyxMlJ899ckjC4wKPfKRoc9www",
        "sPossibleLinkedInEmailAddress": "",
        "bManyLinkedInConnections": true,
        "iLinkedInAccomplishments": 0,
        "iCertifications": "",
        "iLinkedInExperience": 7,
        "iLinkedInEducation": 2,
        "bLinkedInCurrentlyEmployed": true,
        "iFlatIronExperience": 0,
        "iGeneralAssemblyExperience": 0,
        "iUdacityExperience": 0,
        "iCourseraExperience": 0,
        "iUdemyExperience": 0,
        "iAppAcademyExperience": 0,
        "iFlatIronCredentials": 0,
        "iGeneralAssemblyCredentials": 0,
        "iUdacityCredentials": 0,
        "iCourseraCredentials": 0,
        "iUdemyCredentials": 0,
        "iAppAcademyCredentials": 0,
        "iAlternativeCredentialCount": 0,
        "bIsAlternativelyEducated": false,
        "iAlternativeExperienceCount": 0,
        "bIsAlternativelyExperienced": false
    },
    "bKairosImageSubmitted": true,
    "iKairosAge": 33,
    "iKairosAsian": 0.00474,
    "iKairosBlack": 0.01112,
    "iKairosMaleConfidence": 0.99999,
    "iKairosHispanic": 0.042,
    "iKairosOtherEthnicity": 0.00805,
    "iKairosWhite": 0.93408,
    "iLanguagesSpoken": 1,
    "bSpeaksEnglish": true,
    "bSpeaksSpanish": false,
    "bSpeaksOther": false,
    "sState": "MA",
    "sCountry": "United States",
    "bGithubAccountClaimed": false,
    "bGitHubAccountFound": false,
    "bLinkedInAccountClaimed": true,
    "bLinkedInAccountFound": true,
    "sLinkedInFullName": "Jonathan Stickney",
    "sLinkedInPath": "jmstickney",
    "sLinkedInImageUrl": "https://media.licdn.com/dms/image/C4D03AQFDu6vkxUwIPQ/profile-displayphoto-shrink_800_800/0?e=1529654400&v=beta&t=gtC4w_8CNBMqm07HZIyxMlJ899ckjC4wKPfKRoc9www",
    "sPossibleLinkedInEmailAddress": "",
    "bManyLinkedInConnections": true,
    "iLinkedInAccomplishments": 0,
    "iCertifications": "",
    "iLinkedInExperience": 7,
    "iLinkedInEducation": 2,
    "bLinkedInCurrentlyEmployed": true,
    "iFlatIronExperience": 0,
    "iGeneralAssemblyExperience": 0,
    "iUdacityExperience": 0,
    "iCourseraExperience": 0,
    "iUdemyExperience": 0,
    "iAppAcademyExperience": 0,
    "iFlatIronCredentials": 0,
    "iGeneralAssemblyCredentials": 0,
    "iUdacityCredentials": 0,
    "iCourseraCredentials": 0,
    "iUdemyCredentials": 0,
    "iAppAcademyCredentials": 0,
    "iAlternativeCredentialCount": 0,
    "bIsAlternativelyEducated": false,
    "iAlternativeExperienceCount": 0,
    "bIsAlternativelyExperienced": false
}