{
    "bUserExists": true,
    "bProfileIsPrivate": false,
    "bTooManyRequestsError": false,
    "sScrapedUrl": "https://profiles.udacity.com/u/jonathan24",
    "sScrapedUserId": "jonathan24",
    "sProfileLastUpdate": "Profile last updated 9 months ago",
    "sName": "Jonathan",
    "sLocation": "Westborough, MA",
    "sEmail": "jmstickney@gmail.com",
    "sStateOrCountry": "MA",
    "sImageUrl": "https://s3-us-west-2.amazonaws.com/udacity-profiles/production/photo/u11764518.jpg#1522545640533",
    "sLinkedInUrl": "https://www.linkedin.com/in/jmstickney",
    "iDetailCount": 1,
    "iCountOfNanodegrees": 0,
    "iEducationCount": 0,
    "iExperienceCount": 0,
    "bPresentlyEmployed": false,
    "iAgeEstimate": null,
    "sLanguagesSpoken": "English",
    "sImageOnGithubUrl": "https://raw.githubusercontent.com/Vandivier/data-science-practice/master/js/udacity-study/manually-scraped/profile-pics/jonathan24.jpg",
    "sInputLocation": "manually-scraped/broad-sample/jonathan24.txt",
    "sInputBaseName": "broad-sample",
    "sOutputDirectory": "manually-scraped/broad-sample - processed",
    "sOutputLocation": "manually-scraped/broad-sample - processed/jonathan24.json",
    "bNameTruncated": false,
    "iLanguagesSpoken": 1,
    "bSpeaksEnglish": true,
    "bSpeaksSpanish": false,
    "bSpeaksOther": false
}