{
    "bUserExists": true,
    "bProfileIsPrivate": false,
    "bTooManyRequestsError": false,
    "sScrapedUrl": "https://profiles.udacity.com/u/peter",
    "sScrapedUserId": "peter",
    "sProfileLastUpdate": "Profile last updated 9 months ago",
    "sName": "Peter",
    "sLocation": "Durham, NC",
    "sEmail": "peteralan.udacity@gmail.com",
    "sStateOrCountry": "NC",
    "sImageUrl": "https://s3-us-west-2.amazonaws.com/udacity-profiles/production/photo/4502292493.jpg#1522552369728",
    "sLinkedInUrl": "https://www.linkedin.com/profile/view?id=9208513",
    "iDetailCount": 1,
    "iCountOfNanodegrees": 0,
    "iEducationCount": 0,
    "iExperienceCount": 0,
    "bPresentlyEmployed": false,
    "iAgeEstimate": null,
    "sLanguagesSpoken": "None",
    "sImageOnGithubUrl": "https://raw.githubusercontent.com/Vandivier/data-science-practice/master/js/udacity-study/manually-scraped/profile-pics/peter.jpg",
    "sInputLocation": "manually-scraped/broad-sample/peter.txt",
    "sInputBaseName": "broad-sample",
    "sOutputDirectory": "manually-scraped/broad-sample - processed",
    "sOutputLocation": "manually-scraped/broad-sample - processed/peter.json",
    "iLanguagesSpoken": 0,
    "bSpeaksEnglish": false,
    "bSpeaksSpanish": false,
    "bSpeaksOther": false
}