{
    "bUserExists": true,
    "bProfileIsPrivate": false,
    "bTooManyRequestsError": false,
    "sScrapedUrl": "https://profiles.udacity.com/u/rob3",
    "sScrapedUserId": "rob3",
    "sProfileLastUpdate": "Profile last updated 9 months ago",
    "sName": "Rob",
    "sLocation": "Lafayette, LA",
    "sEmail": "rfg8855@att.net",
    "sStateOrCountry": "LA",
    "sImageUrl": "https://s3-us-west-2.amazonaws.com/udacity-profiles/assets/default_profile_picture.png",
    "iDetailCount": 0,
    "iCountOfNanodegrees": 0,
    "iEducationCount": 0,
    "iExperienceCount": 0,
    "bPresentlyEmployed": false,
    "iAgeEstimate": null,
    "sLanguagesSpoken": "English",
    "sImageOnGithubUrl": "https://raw.githubusercontent.com/Vandivier/data-science-practice/master/js/udacity-study/manually-scraped/profile-pics/rob3.jpg",
    "sInputLocation": "manually-scraped/broad-sample/rob3.txt",
    "sInputBaseName": "broad-sample",
    "sOutputDirectory": "manually-scraped/broad-sample - processed",
    "sOutputLocation": "manually-scraped/broad-sample - processed/rob3.json",
    "bNameTruncated": false,
    "sNameAsReported": "Rob",
    "sNameWithoutSuffix": "Rob",
    "sNameWithoutInitials": "Rob",
    "sNameFirst": "Rob",
    "sNameFirstLowercased": "rob",
    "oCachedData": {
        "bUserExists": true,
        "bProfileIsPrivate": false,
        "bTooManyRequestsError": false,
        "sScrapedUrl": "https://profiles.udacity.com/u/rob3",
        "sScrapedUserId": "rob3",
        "sProfileLastUpdate": "Profile last updated 9 months ago",
        "sName": "Rob",
        "sLocation": "Lafayette, LA",
        "sEmail": "rfg8855@att.net",
        "sStateOrCountry": "LA",
        "sImageUrl": "https://s3-us-west-2.amazonaws.com/udacity-profiles/assets/default_profile_picture.png",
        "iDetailCount": 0,
        "iCountOfNanodegrees": 0,
        "iEducationCount": 0,
        "iExperienceCount": 0,
        "bPresentlyEmployed": false,
        "iAgeEstimate": null,
        "sLanguagesSpoken": "English",
        "sImageOnGithubUrl": "https://raw.githubusercontent.com/Vandivier/data-science-practice/master/js/udacity-study/manually-scraped/profile-pics/rob3.jpg",
        "sInputLocation": "manually-scraped/broad-sample/rob3.txt",
        "sInputBaseName": "broad-sample",
        "sOutputDirectory": "manually-scraped/broad-sample - processed",
        "sOutputLocation": "manually-scraped/broad-sample - processed/rob3.json",
        "bNameTruncated": false,
        "sNameAsReported": "Rob",
        "sNameWithoutSuffix": "Rob",
        "sNameWithoutInitials": "Rob",
        "sNameFirst": "Rob",
        "sNameFirstLowercased": "rob",
        "oCachedData": {
            "bUserExists": true,
            "bProfileIsPrivate": false,
            "bTooManyRequestsError": false,
            "sScrapedUrl": "https://profiles.udacity.com/u/rob3",
            "sScrapedUserId": "rob3",
            "sProfileLastUpdate": "Profile last updated 9 months ago",
            "sName": "Rob",
            "sLocation": "Lafayette, LA",
            "sEmail": "rfg8855@att.net",
            "sStateOrCountry": "LA",
            "sImageUrl": "https://s3-us-west-2.amazonaws.com/udacity-profiles/assets/default_profile_picture.png",
            "iDetailCount": 0,
            "iCountOfNanodegrees": 0,
            "iEducationCount": 0,
            "iExperienceCount": 0,
            "bPresentlyEmployed": false,
            "iAgeEstimate": null,
            "sLanguagesSpoken": "English",
            "sImageOnGithubUrl": "https://raw.githubusercontent.com/Vandivier/data-science-practice/master/js/udacity-study/manually-scraped/profile-pics/rob3.jpg",
            "sInputLocation": "manually-scraped/broad-sample/rob3.txt",
            "sInputBaseName": "broad-sample",
            "sOutputDirectory": "manually-scraped/broad-sample - processed",
            "sOutputLocation": "manually-scraped/broad-sample - processed/rob3.json",
            "bNameTruncated": false,
            "sNameAsReported": "Rob",
            "sNameWithoutSuffix": "Rob",
            "sNameWithoutInitials": "Rob",
            "sNameFirst": "Rob",
            "sNameFirstLowercased": "rob",
            "oCachedData": {
                "bUserExists": true,
                "bProfileIsPrivate": false,
                "bTooManyRequestsError": false,
                "sScrapedUrl": "https://profiles.udacity.com/u/rob3",
                "sScrapedUserId": "rob3",
                "sProfileLastUpdate": "Profile last updated 9 months ago",
                "sName": "Rob",
                "sLocation": "Lafayette, LA",
                "sEmail": "rfg8855@att.net",
                "sStateOrCountry": "LA",
                "sImageUrl": "https://s3-us-west-2.amazonaws.com/udacity-profiles/assets/default_profile_picture.png",
                "iDetailCount": 0,
                "iCountOfNanodegrees": 0,
                "iEducationCount": 0,
                "iExperienceCount": 0,
                "bPresentlyEmployed": false,
                "iAgeEstimate": null,
                "sLanguagesSpoken": "English",
                "sImageOnGithubUrl": "https://raw.githubusercontent.com/Vandivier/data-science-practice/master/js/udacity-study/manually-scraped/profile-pics/rob3.jpg",
                "sInputLocation": "manually-scraped/broad-sample/rob3.txt",
                "sInputBaseName": "broad-sample",
                "sOutputDirectory": "manually-scraped/broad-sample - processed",
                "sOutputLocation": "manually-scraped/broad-sample - processed/rob3.json",
                "bNameTruncated": false,
                "sNameAsReported": "Rob",
                "sNameWithoutSuffix": "Rob",
                "sNameWithoutInitials": "Rob",
                "sNameFirst": "Rob",
                "oCachedData": {
                    "bUserExists": true,
                    "bProfileIsPrivate": false,
                    "bTooManyRequestsError": false,
                    "sScrapedUrl": "https://profiles.udacity.com/u/rob3",
                    "sScrapedUserId": "rob3",
                    "sProfileLastUpdate": "Profile last updated 9 months ago",
                    "sName": "Rob",
                    "sLocation": "Lafayette, LA",
                    "sEmail": "rfg8855@att.net",
                    "sStateOrCountry": "LA",
                    "sImageUrl": "https://s3-us-west-2.amazonaws.com/udacity-profiles/assets/default_profile_picture.png",
                    "iDetailCount": 0,
                    "iCountOfNanodegrees": 0,
                    "iEducationCount": 0,
                    "iExperienceCount": 0,
                    "bPresentlyEmployed": false,
                    "iAgeEstimate": null,
                    "sLanguagesSpoken": "English",
                    "sImageOnGithubUrl": "https://raw.githubusercontent.com/Vandivier/data-science-practice/master/js/udacity-study/manually-scraped/profile-pics/rob3.jpg",
                    "sInputLocation": "manually-scraped/broad-sample/rob3.txt",
                    "sInputBaseName": "broad-sample",
                    "sOutputDirectory": "manually-scraped/broad-sample - processed",
                    "sOutputLocation": "manually-scraped/broad-sample - processed/rob3.json",
                    "bNameTruncated": false,
                    "sNameAsReported": "Rob",
                    "sNameWithoutSuffix": "Rob",
                    "sNameWithoutInitials": "Rob",
                    "sNameFirst": "Rob",
                    "oCachedData": {
                        "bUserExists": true,
                        "bProfileIsPrivate": false,
                        "bTooManyRequestsError": false,
                        "sScrapedUrl": "https://profiles.udacity.com/u/rob3",
                        "sScrapedUserId": "rob3",
                        "sProfileLastUpdate": "Profile last updated 9 months ago",
                        "sName": "Rob",
                        "sLocation": "Lafayette, LA",
                        "sEmail": "rfg8855@att.net",
                        "sStateOrCountry": "LA",
                        "sImageUrl": "https://s3-us-west-2.amazonaws.com/udacity-profiles/assets/default_profile_picture.png",
                        "iDetailCount": 0,
                        "iCountOfNanodegrees": 0,
                        "iEducationCount": 0,
                        "iExperienceCount": 0,
                        "bPresentlyEmployed": false,
                        "iAgeEstimate": null,
                        "sLanguagesSpoken": "English",
                        "sImageOnGithubUrl": "https://raw.githubusercontent.com/Vandivier/data-science-practice/master/js/udacity-study/manually-scraped/profile-pics/rob3.jpg",
                        "sInputLocation": "manually-scraped/broad-sample/rob3.txt",
                        "sInputBaseName": "broad-sample",
                        "sOutputDirectory": "manually-scraped/broad-sample - processed",
                        "sOutputLocation": "manually-scraped/broad-sample - processed/rob3.json",
                        "bNameTruncated": false,
                        "sNameAsReported": "Rob",
                        "sNameWithoutSuffix": "Rob",
                        "sNameWithoutInitials": "Rob",
                        "sFirstName": "Rob",
                        "oCachedData": {
                            "bUserExists": true,
                            "bProfileIsPrivate": false,
                            "bTooManyRequestsError": false,
                            "sScrapedUrl": "https://profiles.udacity.com/u/rob3",
                            "sScrapedUserId": "rob3",
                            "sProfileLastUpdate": "Profile last updated 9 months ago",
                            "sName": "Rob",
                            "sLocation": "Lafayette, LA",
                            "sEmail": "rfg8855@att.net",
                            "sStateOrCountry": "LA",
                            "sImageUrl": "https://s3-us-west-2.amazonaws.com/udacity-profiles/assets/default_profile_picture.png",
                            "iDetailCount": 0,
                            "iCountOfNanodegrees": 0,
                            "iEducationCount": 0,
                            "iExperienceCount": 0,
                            "bPresentlyEmployed": false,
                            "iAgeEstimate": null,
                            "sLanguagesSpoken": "English",
                            "sImageOnGithubUrl": "https://raw.githubusercontent.com/Vandivier/data-science-practice/master/js/udacity-study/manually-scraped/profile-pics/rob3.jpg",
                            "sInputLocation": "manually-scraped/broad-sample/rob3.txt",
                            "sInputBaseName": "broad-sample",
                            "sOutputDirectory": "manually-scraped/broad-sample - processed",
                            "sOutputLocation": "manually-scraped/broad-sample - processed/rob3.json",
                            "bNameTruncated": false,
                            "iLanguagesSpoken": 1,
                            "bSpeaksEnglish": true,
                            "bSpeaksSpanish": false,
                            "bSpeaksOther": false,
                            "sState": "LA",
                            "sCountry": "United States",
                            "bGithubAccountClaimed": false,
                            "bGitHubAccountFound": false
                        },
                        "iLanguagesSpoken": 1,
                        "bSpeaksEnglish": true,
                        "bSpeaksSpanish": false,
                        "bSpeaksOther": false,
                        "sState": "LA",
                        "sCountry": "United States",
                        "bGithubAccountClaimed": false,
                        "bGitHubAccountFound": false
                    },
                    "iLanguagesSpoken": 1,
                    "bSpeaksEnglish": true,
                    "bSpeaksSpanish": false,
                    "bSpeaksOther": false,
                    "sState": "LA",
                    "sCountry": "United States",
                    "bGithubAccountClaimed": false,
                    "bGitHubAccountFound": false
                },
                "iLanguagesSpoken": 1,
                "bSpeaksEnglish": true,
                "bSpeaksSpanish": false,
                "bSpeaksOther": false,
                "sState": "LA",
                "sCountry": "United States",
                "bGithubAccountClaimed": false,
                "bGitHubAccountFound": false
            },
            "iLanguagesSpoken": 1,
            "bSpeaksEnglish": true,
            "bSpeaksSpanish": false,
            "bSpeaksOther": false,
            "sState": "LA",
            "sCountry": "United States",
            "bGithubAccountClaimed": false,
            "bGitHubAccountFound": false
        },
        "iLanguagesSpoken": 1,
        "bSpeaksEnglish": true,
        "bSpeaksSpanish": false,
        "bSpeaksOther": false,
        "sState": "LA",
        "sCountry": "United States",
        "bGithubAccountClaimed": false,
        "bGitHubAccountFound": false,
        "bLinkedInAccountClaimed": false,
        "bLinkedInAccountFound": false
    },
    "iLanguagesSpoken": 1,
    "bSpeaksEnglish": true,
    "bSpeaksSpanish": false,
    "bSpeaksOther": false,
    "sState": "LA",
    "sCountry": "United States",
    "bGithubAccountClaimed": false,
    "bGitHubAccountFound": false,
    "bLinkedInAccountClaimed": false,
    "bLinkedInAccountFound": false
}